Workbook

Sheet Inputs
A1: Variable | B1: Value | C1: Notes
A2: Current Year | B2: 2026
A3: Starting Age | B3: 43
A4: Target Retirement Age | B4: 60
A5: Combined Income | B5: 494000 | C5: Gross including super
A6: Living Expenses | B6: 150000 | C6: Annual
A7: Cooroy Purchase Price | B7: 2500000
A8: Wishart Loan Balance | B8: 560000 | C8: Starting balance
A9: Bank Margin (Loans) | B9: 0.02 | C9: Added to RBA rate

Sheet Automated_Data
A1: Metric | B1: Ticker/Source | C1: Value | D1: Last Updated
A2: RBA Cash Rate | B2: RBA API | C2: 0.0435 | D2: 2026-06-27
A3: VTS Price | B3: ASX:VTS | C3: =GOOGLEFINANCE("ASX:VTS", "price") | D3: Automated via Google
A4: NDQ Price | B4: ASX:NDQ | C4: =GOOGLEFINANCE("ASX:NDQ", "price") | D4: Automated via Google
A5: VGS Price | B5: ASX:VGS | C5: =GOOGLEFINANCE("ASX:VGS", "price") | D5: Automated via Google

Sheet Projections
A1: Year | B1: Date | C1: Age | D1: Wishart Loan | E1: Cooroy Loan | F1: ETF Portfolio | G1: Superannuation | H1: Net Worth
A2: =Inputs!B2+0 | B2: 01/01/2026 | C2: =Inputs!B3+0 | D2: =MAX(Inputs!B8-(0*35000), 0) | E2: =Inputs!B7*0.8 | F2: =0*30000 | G2: =800000+(0*45000) | H2: =((Inputs!B7*1.03^0) + (1700000*1.03^0) + (0*30000) + (800000+(0*45000))) - (MAX(Inputs!B8-(0*35000), 0) + (Inputs!B7*0.8))
A3: =Inputs!B2+1 | B3: 01/01/2027 | C3: =Inputs!B3+1 | D3: =MAX(Inputs!B8-(1*35000), 0) | E3: =Inputs!B7*0.8 | F3: =1*30000 | G3: =800000+(1*45000) | H3: =((Inputs!B7*1.03^1) + (1700000*1.03^1) + (1*30000) + (800000+(1*45000))) - (MAX(Inputs!B8-(1*35000), 0) + (Inputs!B7*0.8))
A4: =Inputs!B2+2 | B4: 01/01/2028 | C4: =Inputs!B3+2 | D4: =MAX(Inputs!B8-(2*35000), 0) | E4: =Inputs!B7*0.8 | F4: =2*30000 | G4: =800000+(2*45000) | H4: =((Inputs!B7*1.03^2) + (1700000*1.03^2) + (2*30000) + (800000+(2*45000))) - (MAX(Inputs!B8-(2*35000), 0) + (Inputs!B7*0.8))
A5: =Inputs!B2+3 | B5: 01/01/2029 | C5: =Inputs!B3+3 | D5: =MAX(Inputs!B8-(3*35000), 0) | E5: =Inputs!B7*0.8 | F5: =3*30000 | G5: =800000+(3*45000) | H5: =((Inputs!B7*1.03^3) + (1700000*1.03^3) + (3*30000) + (800000+(3*45000))) - (MAX(Inputs!B8-(3*35000), 0) + (Inputs!B7*0.8))
A6: =Inputs!B2+4 | B6: 01/01/2030 | C6: =Inputs!B3+4 | D6: =MAX(Inputs!B8-(4*35000), 0) | E6: =Inputs!B7*0.8 | F6: =4*30000 | G6: =800000+(4*45000) | H6: =((Inputs!B7*1.03^4) + (1700000*1.03^4) + (4*30000) + (800000+(4*45000))) - (MAX(Inputs!B8-(4*35000), 0) + (Inputs!B7*0.8))
A7: =Inputs!B2+5 | B7: 01/01/2031 | C7: =Inputs!B3+5 | D7: =MAX(Inputs!B8-(5*35000), 0) | E7: =Inputs!B7*0.8 | F7: =5*30000 | G7: =800000+(5*45000) | H7: =((Inputs!B7*1.03^5) + (1700000*1.03^5) + (5*30000) + (800000+(5*45000))) - (MAX(Inputs!B8-(5*35000), 0) + (Inputs!B7*0.8))
A8: =Inputs!B2+6 | B8: 01/01/2032 | C8: =Inputs!B3+6 | D8: =MAX(Inputs!B8-(6*35000), 0) | E8: =Inputs!B7*0.8 | F8: =6*30000 | G8: =800000+(6*45000) | H8: =((Inputs!B7*1.03^6) + (1700000*1.03^6) + (6*30000) + (800000+(6*45000))) - (MAX(Inputs!B8-(6*35000), 0) + (Inputs!B7*0.8))
A9: =Inputs!B2+7 | B9: 01/01/2033 | C9: =Inputs!B3+7 | D9: =MAX(Inputs!B8-(7*35000), 0) | E9: =Inputs!B7*0.8 | F9: =7*30000 | G9: =800000+(7*45000) | H9: =((Inputs!B7*1.03^7) + (1700000*1.03^7) + (7*30000) + (800000+(7*45000))) - (MAX(Inputs!B8-(7*35000), 0) + (Inputs!B7*0.8))
A10: =Inputs!B2+8 | B10: 01/01/2034 | C10: =Inputs!B3+8 | D10: =MAX(Inputs!B8-(8*35000), 0) | E10: =Inputs!B7*0.8 | F10: =8*30000 | G10: =800000+(8*45000) | H10: =((Inputs!B7*1.03^8) + (1700000*1.03^8) + (8*30000) + (800000+(8*45000))) - (MAX(Inputs!B8-(8*35000), 0) + (Inputs!B7*0.8))
A11: =Inputs!B2+9 | B11: 01/01/2035 | C11: =Inputs!B3+9 | D11: =MAX(Inputs!B8-(9*35000), 0) | E11: =Inputs!B7*0.8 | F11: =9*30000 | G11: =800000+(9*45000) | H11: =((Inputs!B7*1.03^9) + (1700000*1.03^9) + (9*30000) + (800000+(9*45000))) - (MAX(Inputs!B8-(9*35000), 0) + (Inputs!B7*0.8))
A12: =Inputs!B2+10 | B12: 01/01/2036 | C12: =Inputs!B3+10 | D12: =MAX(Inputs!B8-(10*35000), 0) | E12: =Inputs!B7*0.8 | F12: =10*30000 | G12: =800000+(10*45000) | H12: =((Inputs!B7*1.03^10) + (1700000*1.03^10) + (10*30000) + (800000+(10*45000))) - (MAX(Inputs!B8-(10*35000), 0) + (Inputs!B7*0.8))
A13: =Inputs!B2+11 | B13: 01/01/2037 | C13: =Inputs!B3+11 | D13: =MAX(Inputs!B8-(11*35000), 0) | E13: =Inputs!B7*0.8 | F13: =11*30000 | G13: =800000+(11*45000) | H13: =((Inputs!B7*1.03^11) + (1700000*1.03^11) + (11*30000) + (800000+(11*45000))) - (MAX(Inputs!B8-(11*35000), 0) + (Inputs!B7*0.8))
A14: =Inputs!B2+12 | B14: 01/01/2038 | C14: =Inputs!B3+12 | D14: =MAX(Inputs!B8-(12*35000), 0) | E14: =Inputs!B7*0.8 | F14: =12*30000 | G14: =800000+(12*45000) | H14: =((Inputs!B7*1.03^12) + (1700000*1.03^12) + (12*30000) + (800000+(12*45000))) - (MAX(Inputs!B8-(12*35000), 0) + (Inputs!B7*0.8))
A15: =Inputs!B2+13 | B15: 01/01/2039 | C15: =Inputs!B3+13 | D15: =MAX(Inputs!B8-(13*35000), 0) | E15: =Inputs!B7*0.8 | F15: =13*30000 | G15: =800000+(13*45000) | H15: =((Inputs!B7*1.03^13) + (1700000*1.03^13) + (13*30000) + (800000+(13*45000))) - (MAX(Inputs!B8-(13*35000), 0) + (Inputs!B7*0.8))
A16: =Inputs!B2+14 | B16: 01/01/2040 | C16: =Inputs!B3+14 | D16: =MAX(Inputs!B8-(14*35000), 0) | E16: =Inputs!B7*0.8 | F16: =14*30000 | G16: =800000+(14*45000) | H16: =((Inputs!B7*1.03^14) + (1700000*1.03^14) + (14*30000) + (800000+(14*45000))) - (MAX(Inputs!B8-(14*35000), 0) + (Inputs!B7*0.8))
A17: =Inputs!B2+15 | B17: 01/01/2041 | C17: =Inputs!B3+15 | D17: =MAX(Inputs!B8-(15*35000), 0) | E17: =Inputs!B7*0.8 | F17: =15*30000 | G17: =800000+(15*45000) | H17: =((Inputs!B7*1.03^15) + (1700000*1.03^15) + (15*30000) + (800000+(15*45000))) - (MAX(Inputs!B8-(15*35000), 0) + (Inputs!B7*0.8))
A18: =Inputs!B2+16 | B18: 01/01/2042 | C18: =Inputs!B3+16 | D18: =MAX(Inputs!B8-(16*35000), 0) | E18: =Inputs!B7*0.8 | F18: =16*30000 | G18: =800000+(16*45000) | H18: =((Inputs!B7*1.03^16) + (1700000*1.03^16) + (16*30000) + (800000+(16*45000))) - (MAX(Inputs!B8-(16*35000), 0) + (Inputs!B7*0.8))
A19: =Inputs!B2+17 | B19: 01/01/2043 | C19: =Inputs!B3+17 | D19: =MAX(Inputs!B8-(17*35000), 0) | E19: =Inputs!B7*0.8 | F19: =17*30000 | G19: =800000+(17*45000) | H19: =((Inputs!B7*1.03^17) + (1700000*1.03^17) + (17*30000) + (800000+(17*45000))) - (MAX(Inputs!B8-(17*35000), 0) + (Inputs!B7*0.8))
